LICENSE.md
README.md
setup.cfg
setup.py
tmil/__init__.py
tmil/tmil.py
tmil.egg-info/PKG-INFO
tmil.egg-info/SOURCES.txt
tmil.egg-info/dependency_links.txt
tmil.egg-info/requires.txt
tmil.egg-info/top_level.txt